[
    {
        "status": true,
        "message": "Success",
        "timestamp": 1692829626253,
        "data": [
            {
                "title": "<b>Dhaka City</b>",
                "geoId": "loc;293936;g293936",
                "documentId": "loc;293936;g293936",
                "trackingItems": "geo",
                "secondaryText": "Dhaka Division, Bangladesh"
            },
            {
                "title": "<b>Dhaka Division</b>",
                "geoId": "loc;667479;g667479",
                "documentId": "loc;667479;g667479",
                "trackingItems": "geo",
                "secondaryText": "Bangladesh, Asia"
            },
            {
                "title": "<b>Amari Dhaka Bangladesh</b>",
                "geoId": "loc;6985943",
                "documentId": "loc;6985943",
                "trackingItems": "hotel",
                "secondaryText": "Dhaka City, Bangladesh",
                "image": {
                    "__typename": "AppPresentation_PhotoItemSizeDynamic",
                    "maxHeight": 585,
                    "maxWidth": 1123,
                    "urlTemplate": "https://dynamic-media-cdn.tripadvisor.com/media/photo-o/29/08/c6/62/amari-dhaka-arial-shot.jpg?w={width}&h={height}&s=1"
                }
            },
            {
                "title": "<b>Radisson Blu Dhaka Water Garden</b>",
                "geoId": "loc;603313",
                "documentId": "loc;603313",
                "trackingItems": "hotel",
                "secondaryText": "Dhaka City, Bangladesh",
                "image": {
                    "__typename": "AppPresentation_PhotoItemSizeDynamic",
                    "maxHeight": 670,
                    "maxWidth": 1023,
                    "urlTemplate": "https://dynamic-media-cdn.tripadvisor.com/media/photo-o/21/72/27/7e/exterior.jpg?w={width}&h={height}&s=1"
                }
            },
            {
                "title": "<b>Pan Pacific Sonargaon Dhaka</b>",
                "geoId": "loc;301905",
                "documentId": "loc;301905",
                "trackingItems": "hotel",
                "secondaryText": "Dhaka City, Bangladesh",
                "image": {
                    "__typename": "AppPresentation_PhotoItemSizeDynamic",
                    "maxHeight": 661,
                    "maxWidth": 1024,
                    "urlTemplate": "https://dynamic-media-cdn.tripadvisor.com/media/photo-o/1a/36/a3/58/international-suite.jpg?w={width}&h={height}&s=1"
                }
            },
            {
                "title": "<b>InterContinental Dhaka, an IHG Hotel</b>",
                "geoId": "loc;9724717",
                "documentId": "loc;9724717",
                "trackingItems": "hotel",
                "secondaryText": "Dhaka City, Bangladesh",
                "image": {
                    "__typename": "AppPresentation_PhotoItemSizeDynamic",
                    "maxHeight": 2160,
                    "maxWidth": 3840,
                    "urlTemplate": "https://dynamic-media-cdn.tripadvisor.com/media/photo-o/29/36/38/12/landscape.jpg?w={width}&h={height}&s=1"
                }
            },
            {
                "title": "<b>The Westin Dhaka</b>",
                "geoId": "loc;628632",
                "documentId": "loc;628632",
                "trackingItems": "hotel",
                "secondaryText": "Dhaka City, Bangladesh",
                "image": {
                    "__typename": "AppPresentation_PhotoItemSizeDynamic",
                    "maxHeight": 2667,
                    "maxWidth": 4000,
                    "urlTemplate": "https://dynamic-media-cdn.tripadvisor.com/media/photo-o/29/0c/cb/10/exterior.jpg?w={width}&h={height}&s=1"
                }
            },
            {
                "title": "<b>Le M\u00e9ridien Dhaka</b>",
                "geoId": "loc;7850970",
                "documentId": "loc;7850970",
                "trackingItems": "hotel",
                "secondaryText": "Dhaka City, Bangladesh",
                "image": {
                    "__typename": "AppPresentation_PhotoItemSizeDynamic",
                    "maxHeight": 3795,
                    "maxWidth": 4453,
                    "urlTemplate": "https://dynamic-media-cdn.tripadvisor.com/media/photo-o/1a/1e/5f/cf/exterior-of-the-hotel.jpg?w={width}&h={height}&s=1"
                }
            },
            {
                "title": "Add a missing place",
                "geoId": null,
                "documentId": null,
                "trackingItems": null
            }
        ],
        "city_id": 1,
        "city_name": "Dhaka"
    },
    {
        "status": true,
        "message": "Success",
        "timestamp": 1692829627710,
        "data": [
            {
                "title": "<b>Chittagong City</b>",
                "geoId": "loc;319837;g319837",
                "documentId": "loc;319837;g319837",
                "trackingItems": "geo",
                "secondaryText": "Chittagong Division, Bangladesh"
            },
            {
                "title": "<b>Chittagong Division</b>",
                "geoId": "loc;667480;g667480",
                "documentId": "loc;667480;g667480",
                "trackingItems": "geo",
                "secondaryText": "Bangladesh, Asia"
            },
            {
                "title": "<b>The Peninsula Chittagong</b>",
                "geoId": "loc;1021164",
                "documentId": "loc;1021164",
                "trackingItems": "hotel",
                "secondaryText": "Chittagong City, Bangladesh",
                "image": {
                    "__typename": "AppPresentation_PhotoItemSizeDynamic",
                    "maxHeight": 2075,
                    "maxWidth": 3570,
                    "urlTemplate": "https://dynamic-media-cdn.tripadvisor.com/media/photo-o/29/c6/3b/41/hotel-entrance.jpg?w={width}&h={height}&s=1"
                }
            },
            {
                "title": "<b>Chittagong Club</b>",
                "geoId": "loc;2459449",
                "documentId": "loc;2459449",
                "trackingItems": "hotel",
                "secondaryText": "Chittagong City, Bangladesh",
                "image": {
                    "__typename": "AppPresentation_PhotoItemSizeDynamic",
                    "maxHeight": 470,
                    "maxWidth": 800,
                    "urlTemplate": "https://dynamic-media-cdn.tripadvisor.com/media/photo-o/04/b9/93/65/chittagong-club.jpg?w={width}&h={height}&s=1"
                }
            },
            {
                "title": "<b>Chittagong Chinese Guesthouse</b>",
                "geoId": "loc;3297602",
                "documentId": "loc;3297602",
                "trackingItems": "hotel",
                "secondaryText": "Chittagong City, Bangladesh"
            },
            {
                "title": "Add a missing place",
                "geoId": null,
                "documentId": null,
                "trackingItems": null
            }
        ],
        "city_id": 2,
        "city_name": "Chittagong"
    },
    {
        "status": true,
        "message": "Success",
        "timestamp": 1692829628936,
        "data": [
            {
                "title": "<b>Khulna City</b>",
                "geoId": "loc;667472;g667472",
                "documentId": "loc;667472;g667472",
                "trackingItems": "geo",
                "secondaryText": "Khulna Division, Bangladesh"
            },
            {
                "title": "<b>Khulna Division</b>",
                "geoId": "loc;667481;g667481",
                "documentId": "loc;667481;g667481",
                "trackingItems": "geo",
                "secondaryText": "Bangladesh, Asia"
            },
            {
                "title": "<b>Khulna Club</b>",
                "geoId": "loc;3218319",
                "documentId": "loc;3218319",
                "trackingItems": "hotel",
                "secondaryText": "Khulna City, Bangladesh"
            },
            {
                "title": "<b>Tiger Garden International Hotel, Khulna Bangladesh</b>",
                "geoId": "loc;3218407",
                "documentId": "loc;3218407",
                "trackingItems": "hotel",
                "secondaryText": "Khulna City, Bangladesh",
                "image": {
                    "__typename": "AppPresentation_PhotoItemSizeDynamic",
                    "maxHeight": 1333,
                    "maxWidth": 2000,
                    "urlTemplate": "https://dynamic-media-cdn.tripadvisor.com/media/photo-o/0e/9c/05/91/presidential-suite-master.jpg?w={width}&h={height}&s=1"
                }
            },
            {
                "title": "Add a missing place",
                "geoId": null,
                "documentId": null,
                "trackingItems": null
            }
        ],
        "city_id": 3,
        "city_name": "Khulna"
    },
    {
        "status": true,
        "message": "Success",
        "timestamp": 1692829630006,
        "data": [
            {
                "title": "<b>Rajshahi City</b>",
                "geoId": "loc;667998;g667998",
                "documentId": "loc;667998;g667998",
                "trackingItems": "geo",
                "secondaryText": "Rajshahi Division, Bangladesh"
            },
            {
                "title": "<b>Rajshahi Division</b>",
                "geoId": "loc;667482;g667482",
                "documentId": "loc;667482;g667482",
                "trackingItems": "geo",
                "secondaryText": "Bangladesh, Asia"
            },
            {
                "title": "<b>Jatra Flagship Rajshahi City Centre</b>",
                "geoId": "loc;23508062",
                "documentId": "loc;23508062",
                "trackingItems": "hotel",
                "secondaryText": "Rajshahi City, Bangladesh",
                "image": {
                    "__typename": "AppPresentation_PhotoItemSizeDynamic",
                    "maxHeight": 1040,
                    "maxWidth": 1560,
                    "urlTemplate": "https://dynamic-media-cdn.tripadvisor.com/media/photo-o/1d/48/bf/3d/each-of-our-non-smoking.jpg?w={width}&h={height}&s=1"
                }
            },
            {
                "title": "Add a missing place",
                "geoId": null,
                "documentId": null,
                "trackingItems": null
            }
        ],
        "city_id": 4,
        "city_name": "Rajshahi"
    },
    {
        "status": true,
        "message": "Success",
        "timestamp": 1692829631171,
        "data": [
            {
                "title": "<b>Comilla</b>",
                "geoId": "loc;667466;g667466",
                "documentId": "loc;667466;g667466",
                "trackingItems": "geo",
                "secondaryText": "Chittagong Division, Bangladesh"
            },
            {
                "title": "Add a missing place",
                "geoId": null,
                "documentId": null,
                "trackingItems": null
            }
        ],
        "city_id": 5,
        "city_name": "Comilla"
    },
    {
        "status": true,
        "message": "Success",
        "timestamp": 1692829632114,
        "data": [
            {
                "title": "<b>Mymensingh</b>",
                "geoId": "loc;11801509;g11801509",
                "documentId": "loc;11801509;g11801509",
                "trackingItems": "geo",
                "secondaryText": "Bangladesh, Asia"
            },
            {
                "title": "<b>Mymensing</b>",
                "geoId": "loc;668002;g668002",
                "documentId": "loc;668002;g668002",
                "trackingItems": "geo",
                "secondaryText": "Dhaka Division, Bangladesh"
            },
            {
                "title": "<b>Greenscape Eco Resort Bangladesh</b>",
                "geoId": "loc;23657903",
                "documentId": "loc;23657903",
                "trackingItems": "hotel",
                "secondaryText": "Mymensingh, Bangladesh",
                "image": {
                    "__typename": "AppPresentation_PhotoItemSizeDynamic",
                    "maxHeight": 1393,
                    "maxWidth": 2560,
                    "urlTemplate": "https://dynamic-media-cdn.tripadvisor.com/media/photo-o/1e/ac/76/fa/greenscape-resort-bangladesh.jpg?w={width}&h={height}&s=1"
                }
            },
            {
                "title": "Add a missing place",
                "geoId": null,
                "documentId": null,
                "trackingItems": null
            }
        ],
        "city_id": 6,
        "city_name": "Mymensingh"
    },
    {
        "status": true,
        "message": "Success",
        "timestamp": 1692829633522,
        "data": [
            {
                "title": "<b>Rangpur</b>",
                "geoId": "loc;667999;g667999",
                "documentId": "loc;667999;g667999",
                "trackingItems": "geo",
                "secondaryText": "Rajshahi Division, Bangladesh"
            },
            {
                "title": "<b>Rangpur Division</b>",
                "geoId": "loc;3698380;g3698380",
                "documentId": "loc;3698380;g3698380",
                "trackingItems": "geo",
                "secondaryText": "Bangladesh, Asia"
            },
            {
                "title": "<b>Grand Palace Hotel & Resorts Rangpur</b>",
                "geoId": "loc;13792741",
                "documentId": "loc;13792741",
                "trackingItems": "hotel",
                "secondaryText": "Rangpur, Bangladesh",
                "image": {
                    "__typename": "AppPresentation_PhotoItemSizeDynamic",
                    "maxHeight": 366,
                    "maxWidth": 550,
                    "urlTemplate": "https://dynamic-media-cdn.tripadvisor.com/media/photo-o/14/35/80/54/grand-palace-hotel-resorts.jpg?w={width}&h={height}&s=1"
                }
            },
            {
                "title": "<b>Little Rangpur Inn</b>",
                "geoId": "loc;14920486",
                "documentId": "loc;14920486",
                "trackingItems": "hotel",
                "secondaryText": "Rangpur, Bangladesh",
                "image": {
                    "__typename": "AppPresentation_PhotoItemSizeDynamic",
                    "maxHeight": 1536,
                    "maxWidth": 2048,
                    "urlTemplate": "https://dynamic-media-cdn.tripadvisor.com/media/photo-o/16/7c/4a/3d/wonderful-hotel-very.jpg?w={width}&h={height}&s=1"
                }
            },
            {
                "title": "Add a missing place",
                "geoId": null,
                "documentId": null,
                "trackingItems": null
            }
        ],
        "city_id": 7,
        "city_name": "Rangpur"
    },
    {
        "status": true,
        "message": "Success",
        "timestamp": 1692829635515,
        "data": [
            {
                "title": "<b>Sylhet City</b>",
                "geoId": "loc;667997;g667997",
                "documentId": "loc;667997;g667997",
                "trackingItems": "geo",
                "secondaryText": "Sylhet Division, Bangladesh"
            },
            {
                "title": "<b>Sylhet Division</b>",
                "geoId": "loc;667483;g667483",
                "documentId": "loc;667483;g667483",
                "trackingItems": "geo",
                "secondaryText": "Bangladesh, Asia"
            },
            {
                "title": "<b>Grand Sylhet Hotel & Resort</b>",
                "geoId": "loc;23981995",
                "documentId": "loc;23981995",
                "trackingItems": "hotel",
                "secondaryText": "Sylhet City, Bangladesh",
                "image": {
                    "__typename": "AppPresentation_PhotoItemSizeDynamic",
                    "maxHeight": 768,
                    "maxWidth": 1024,
                    "urlTemplate": "https://dynamic-media-cdn.tripadvisor.com/media/photo-o/26/e2/9f/60/grand-sylhet-hotel-resort.jpg?w={width}&h={height}&s=1"
                }
            },
            {
                "title": "Add a missing place",
                "geoId": null,
                "documentId": null,
                "trackingItems": null
            }
        ],
        "city_id": 8,
        "city_name": "Sylhet"
    },
    {
        "status": true,
        "message": "Success",
        "timestamp": 1692829636685,
        "data": [
            {
                "title": "<b>Barisal City</b>",
                "geoId": "loc;667461;g667461",
                "documentId": "loc;667461;g667461",
                "trackingItems": "geo",
                "secondaryText": "Barisal Division, Bangladesh"
            },
            {
                "title": "<b>Barisal Division</b>",
                "geoId": "loc;667484;g667484",
                "documentId": "loc;667484;g667484",
                "trackingItems": "geo",
                "secondaryText": "Bangladesh, Asia"
            },
            {
                "title": "<b>Hotel Arena Barisal</b>",
                "geoId": "loc;8422742",
                "documentId": "loc;8422742",
                "trackingItems": "hotel",
                "secondaryText": "Barisal City, Bangladesh",
                "image": {
                    "__typename": "AppPresentation_PhotoItemSizeDynamic",
                    "maxHeight": 1021,
                    "maxWidth": 768,
                    "urlTemplate": "https://dynamic-media-cdn.tripadvisor.com/media/photo-o/16/94/fe/bc/at-reception.jpg?w={width}&h={height}&s=1"
                }
            },
            {
                "title": "Add a missing place",
                "geoId": null,
                "documentId": null,
                "trackingItems": null
            }
        ],
        "city_id": 9,
        "city_name": "Barisal"
    },
    {
        "status": true,
        "message": "Success",
        "timestamp": 1692829638344,
        "data": [
            {
                "title": "<b>Narayanganj</b>",
                "geoId": "loc;668001;g668001",
                "documentId": "loc;668001;g668001",
                "trackingItems": "geo",
                "secondaryText": "Dhaka Division, Bangladesh"
            },
            {
                "title": "Add a missing place",
                "geoId": null,
                "documentId": null,
                "trackingItems": null
            }
        ],
        "city_id": 10,
        "city_name": "Narayanganj"
    },
    {
        "status": true,
        "message": "Success",
        "timestamp": 1692829639806,
        "data": [
            {
                "title": "<b>Gazipur</b>",
                "geoId": "loc;790459;g790459",
                "documentId": "loc;790459;g790459",
                "trackingItems": "geo",
                "secondaryText": "Dhaka Division, Bangladesh"
            },
            {
                "title": "Add a missing place",
                "geoId": null,
                "documentId": null,
                "trackingItems": null
            }
        ],
        "city_id": 11,
        "city_name": "Gazipur"
    },
    {
        "status": true,
        "message": "Success",
        "timestamp": 1692866589721,
        "data": [
            {
                "title": "<b>Feni</b>",
                "geoId": "loc;17484422;g17484422",
                "documentId": "loc;17484422;g17484422",
                "trackingItems": "geo",
                "secondaryText": "Chittagong Division, Bangladesh"
            },
            {
                "title": "Add a missing place",
                "geoId": null,
                "documentId": null,
                "trackingItems": null
            }
        ],
        "city_id": 12,
        "city_name": "Feni"
    },
    {
        "status": true,
        "message": "Success",
        "timestamp": 1692829641856,
        "data": [
            {
                "title": "<b>Bogra</b>",
                "geoId": "loc;667465;g667465",
                "documentId": "loc;667465;g667465",
                "trackingItems": "geo",
                "secondaryText": "Rajshahi Division, Bangladesh"
            },
            {
                "title": "Add a missing place",
                "geoId": null,
                "documentId": null,
                "trackingItems": null
            }
        ],
        "city_id": 13,
        "city_name": "Bogra"
    },
    {
        "status": true,
        "message": "Success",
        "timestamp": 1692829642959,
        "data": [
            {
                "title": "<b>Pabna</b>",
                "geoId": "loc;668000;g668000",
                "documentId": "loc;668000;g668000",
                "trackingItems": "geo",
                "secondaryText": "Rajshahi Division, Bangladesh"
            },
            {
                "title": "Add a missing place",
                "geoId": null,
                "documentId": null,
                "trackingItems": null
            }
        ],
        "city_id": 14,
        "city_name": "Pabna"
    },
    {
        "status": true,
        "message": "Success",
        "timestamp": 1692829644221,
        "data": [
            {
                "title": "<b>Bandarban</b>",
                "geoId": "loc;2368232;g2368232",
                "documentId": "loc;2368232;g2368232",
                "trackingItems": "geo",
                "secondaryText": "Chittagong Division, Bangladesh"
            },
            {
                "title": "<b>Bandarban Bono Nibas Hill Resort</b>",
                "geoId": "loc;13085442",
                "documentId": "loc;13085442",
                "trackingItems": "hotel",
                "secondaryText": "Bandarban, Bangladesh",
                "image": {
                    "__typename": "AppPresentation_PhotoItemSizeDynamic",
                    "maxHeight": 720,
                    "maxWidth": 1080,
                    "urlTemplate": "https://dynamic-media-cdn.tripadvisor.com/media/photo-o/17/10/6c/6f/bono-nibas-hill-resort.jpg?w={width}&h={height}&s=1"
                }
            },
            {
                "title": "<b>Bandarban Parjatan Motel</b>",
                "geoId": "loc;3557279",
                "documentId": "loc;3557279",
                "trackingItems": "hotel",
                "secondaryText": "Bandarban, Bangladesh",
                "image": {
                    "__typename": "AppPresentation_PhotoItemSizeDynamic",
                    "maxHeight": 1536,
                    "maxWidth": 2048,
                    "urlTemplate": "https://dynamic-media-cdn.tripadvisor.com/media/photo-o/18/67/32/66/bandarban-is-a-hill-are.jpg?w={width}&h={height}&s=1"
                }
            },
            {
                "title": "Add a missing place",
                "geoId": null,
                "documentId": null,
                "trackingItems": null
            }
        ],
        "city_id": 15,
        "city_name": "Bandarban"
    },
    {
        "status": true,
        "message": "Success",
        "timestamp": 1692829645658,
        "data": [
            {
                "title": "<b>Jessore</b>",
                "geoId": "loc;667471;g667471",
                "documentId": "loc;667471;g667471",
                "trackingItems": "geo",
                "secondaryText": "Khulna Division, Bangladesh"
            },
            {
                "title": "Add a missing place",
                "geoId": null,
                "documentId": null,
                "trackingItems": null
            }
        ],
        "city_id": 16,
        "city_name": "Jessore"
    },
    {
        "status": true,
        "message": "Success",
        "timestamp": 1692829646831,
        "data": [
            {
                "title": "<b>Dinajpur</b>",
                "geoId": "loc;2214143;g2214143",
                "documentId": "loc;2214143;g2214143",
                "trackingItems": "geo",
                "secondaryText": "Rajshahi Division, Bangladesh"
            },
            {
                "title": "Add a missing place",
                "geoId": null,
                "documentId": null,
                "trackingItems": null
            }
        ],
        "city_id": 17,
        "city_name": "Dinajpur"
    },
    {
        "status": true,
        "message": "Success",
        "timestamp": 1692829647888,
        "data": [
            {
                "title": "<b>Naogaon</b>",
                "geoId": "loc;11879478;g11879478",
                "documentId": "loc;11879478;g11879478",
                "trackingItems": "geo",
                "secondaryText": "Rajshahi Division, Bangladesh"
            },
            {
                "title": "Add a missing place",
                "geoId": null,
                "documentId": null,
                "trackingItems": null
            }
        ],
        "city_id": 18,
        "city_name": "Naogaon"
    },
    {
        "status": true,
        "message": "Success",
        "timestamp": 1692829649036,
        "data": [
            {
                "title": "<b>Tangail</b>",
                "geoId": "loc;4971747;g4971747",
                "documentId": "loc;4971747;g4971747",
                "trackingItems": "geo",
                "secondaryText": "Dhaka Division, Bangladesh"
            },
            {
                "title": "Add a missing place",
                "geoId": null,
                "documentId": null,
                "trackingItems": null
            }
        ],
        "city_id": 19,
        "city_name": "Tangail"
    },
    {
        "status": true,
        "message": "Success",
        "timestamp": 1692829650007,
        "data": [
            {
                "title": "<b>Netrakona</b>",
                "geoId": "loc;11804434;g11804434",
                "documentId": "loc;11804434;g11804434",
                "trackingItems": "geo",
                "secondaryText": "Bangladesh, Asia"
            },
            {
                "title": "Add a missing place",
                "geoId": null,
                "documentId": null,
                "trackingItems": null
            }
        ],
        "city_id": 20,
        "city_name": "Netrokona"
    },
    {
        "status": true,
        "message": "Success",
        "timestamp": 1692874829848,
        "data": [
            {
                "title": "<b>Savar</b>",
                "geoId": "loc;2167645;g2167645",
                "documentId": "loc;2167645;g2167645",
                "trackingItems": "geo",
                "secondaryText": "Dhaka Division, Bangladesh"
            },
            {
                "title": "<b>BRAC CDM Savar</b>",
                "geoId": "loc;12679650",
                "documentId": "loc;12679650",
                "trackingItems": "hotel",
                "secondaryText": "Savar, Bangladesh",
                "image": {
                    "__typename": "AppPresentation_PhotoItemSizeDynamic",
                    "maxHeight": 1186,
                    "maxWidth": 2000,
                    "urlTemplate": "https://dynamic-media-cdn.tripadvisor.com/media/photo-o/10/0c/bc/8a/deluxe-twin-room.jpg?w={width}&h={height}&s=1"
                }
            },
            {
                "title": "Add a missing place",
                "geoId": null,
                "documentId": null,
                "trackingItems": null
            }
        ],
        "city_id": 21,
        "city_name": "Savar"
    },
    {
        "status": true,
        "message": "Success",
        "timestamp": 1692875360133,
        "data": [
            {
                "title": "<b>Bhairab Bazaar</b>",
                "geoId": "loc;20054980;g20054980",
                "documentId": "loc;20054980;g20054980",
                "trackingItems": "geo",
                "secondaryText": "Dhaka Division, Bangladesh"
            },
            {
                "title": "Add a missing place",
                "geoId": null,
                "documentId": null,
                "trackingItems": null
            }
        ],
        "city_id": 22,
        "city_name": "Bhairab"
    },
    {
        "status": true,
        "message": "Success",
        "timestamp": 1692861489836,
        "data": [
            {
                "title": "<b>Bagerhat</b>",
                "geoId": "loc;325571;g325571",
                "documentId": "loc;325571;g325571",
                "trackingItems": "geo",
                "secondaryText": "Khulna Division, Bangladesh"
            },
            {
                "title": "Add a missing place",
                "geoId": null,
                "documentId": null,
                "trackingItems": null
            }
        ],
        "city_id": 23,
        "city_name": "Bagerhat"
    },
    {
        "status": true,
        "message": "Success",
        "timestamp": 1692896987442,
        "data": [
            {
                "title": "<b>Jhenaidah</b>",
                "geoId": "loc;8552240;g8552240",
                "documentId": "loc;8552240;g8552240",
                "trackingItems": "geo",
                "secondaryText": "Khulna Division, Bangladesh"
            },
            {
                "title": "Add a missing place",
                "geoId": null,
                "documentId": null,
                "trackingItems": null
            }
        ],
        "city_id": 24,
        "city_name": "Jhenaidah"
    },
    {
        "status": true,
        "message": "Success",
        "timestamp": 1692829776496,
        "data": [
            {
                "title": "<b>Bhola</b>",
                "geoId": "loc;667463;g667463",
                "documentId": "loc;667463;g667463",
                "trackingItems": "geo",
                "secondaryText": "Barisal Division, Bangladesh"
            },
            {
                "title": "Add a missing place",
                "geoId": null,
                "documentId": null,
                "trackingItems": null
            }
        ],
        "city_id": 25,
        "city_name": "Bhola"
    },
    {
        "status": true,
        "message": "Success",
        "timestamp": 1692829777665,
        "data": [
            {
                "title": "<b>Manikganj</b>",
                "geoId": "loc;3445218;g3445218",
                "documentId": "loc;3445218;g3445218",
                "trackingItems": "geo",
                "secondaryText": "Dhaka Division, Bangladesh"
            },
            {
                "title": "Add a missing place",
                "geoId": null,
                "documentId": null,
                "trackingItems": null
            }
        ],
        "city_id": 26,
        "city_name": "Manikganj"
    },
    {
        "status": true,
        "message": "Success",
        "timestamp": 1692829778803,
        "data": [
            {
                "title": "<b>Cox's Bazar</b>",
                "geoId": "loc;667467;g667467",
                "documentId": "loc;667467;g667467",
                "trackingItems": "geo",
                "secondaryText": "Chittagong Division, Bangladesh"
            },
            {
                "title": "<b>Sea Pearl Beach Resort & Spa Cox's Bazar</b>",
                "geoId": "loc;8092586",
                "documentId": "loc;8092586",
                "trackingItems": "hotel",
                "secondaryText": "Cox's Bazar, Bangladesh",
                "image": {
                    "__typename": "AppPresentation_PhotoItemSizeDynamic",
                    "maxHeight": 682,
                    "maxWidth": 1023,
                    "urlTemplate": "https://dynamic-media-cdn.tripadvisor.com/media/photo-o/28/91/f6/ce/bathroom.jpg?w={width}&h={height}&s=1"
                }
            },
            {
                "title": "<b>Cox's Bazar Surf Club</b>",
                "geoId": "loc;7258006",
                "documentId": "loc;7258006",
                "trackingItems": "hotel",
                "secondaryText": "Cox's Bazar, Bangladesh",
                "image": {
                    "__typename": "AppPresentation_PhotoItemSizeDynamic",
                    "maxHeight": 1333,
                    "maxWidth": 2000,
                    "urlTemplate": "https://dynamic-media-cdn.tripadvisor.com/media/photo-o/07/ae/95/be/cox-s-bazar-surf-club.jpg?w={width}&h={height}&s=1"
                }
            },
            {
                "title": "Add a missing place",
                "geoId": null,
                "documentId": null,
                "trackingItems": null
            }
        ],
        "city_id": 27,
        "city_name": "Coxs Bazar"
    },
    {
        "status": true,
        "message": "Success",
        "timestamp": 1692829779987,
        "data": [
            {
                "title": "<b>Rangamati</b>",
                "geoId": "loc;2398418;g2398418",
                "documentId": "loc;2398418;g2398418",
                "trackingItems": "geo",
                "secondaryText": "Chittagong Division, Bangladesh"
            },
            {
                "title": "<b>Rangamati Water Front Resort</b>",
                "geoId": "loc;4500593",
                "documentId": "loc;4500593",
                "trackingItems": "hotel",
                "secondaryText": "Dhaka City, Bangladesh",
                "image": {
                    "__typename": "AppPresentation_PhotoItemSizeDynamic",
                    "maxHeight": 1536,
                    "maxWidth": 2048,
                    "urlTemplate": "https://dynamic-media-cdn.tripadvisor.com/media/photo-o/17/17/66/5a/photo3jpg.jpg?w={width}&h={height}&s=1"
                }
            },
            {
                "title": "Add a missing place",
                "geoId": null,
                "documentId": null,
                "trackingItems": null
            }
        ],
        "city_id": 28,
        "city_name": "Rangamati"
    },
    {
        "status": true,
        "message": "Success",
        "timestamp": 1692829871464,
        "data": [
            {
                "title": "<b>Tangail</b>",
                "geoId": "loc;4971747;g4971747",
                "documentId": "loc;4971747;g4971747",
                "trackingItems": "geo",
                "secondaryText": "Dhaka Division, Bangladesh"
            },
            {
                "title": "Add a missing place",
                "geoId": null,
                "documentId": null,
                "trackingItems": null
            }
        ],
        "city_id": 29,
        "city_name": "Tangail"
    },
    {
        "status": true,
        "message": "Success",
        "timestamp": 1692829872632,
        "data": [
            {
                "title": "<b>Chandpur</b>",
                "geoId": "loc;1202565;g1202565",
                "documentId": "loc;1202565;g1202565",
                "trackingItems": "geo",
                "secondaryText": "Chittagong Division, Bangladesh"
            },
            {
                "title": "Add a missing place",
                "geoId": null,
                "documentId": null,
                "trackingItems": null
            }
        ],
        "city_id": 30,
        "city_name": "Chandpur"
    }
]